pyExploringCodeDOMParser/__init__.py
pyExploringCodeDOMParser-1.1.4.dist-info/LICENSE.md
pyExploringCodeDOMParser-1.1.4.dist-info/METADATA
pyExploringCodeDOMParser-1.1.4.dist-info/WHEEL
pyExploringCodeDOMParser-1.1.4.dist-info/top_level.txt
pyExploringCodeDOMParser-1.1.4.dist-info/RECORD
